virtualbox_helper/__init__.py
virtualbox_helper-0.1.2.dist-info/entry_points.txt
virtualbox_helper-0.1.2.dist-info/LICENSE.md
virtualbox_helper-0.1.2.dist-info/WHEEL
virtualbox_helper-0.1.2.dist-info/METADATA
virtualbox_helper-0.1.2.dist-info/RECORD
