Metadata-Version: 2.1
Name: virtualbox-helper
Version: 0.1.2
Summary: Start and control a virtualbox machine
Home-page: https://github.com/jacopofar/virtualbox-helper
License: MIT
Keywords: virtualbox,opencv
Author: Jacopo Farina
Author-email: jacopo1.farina@gmail.com
Requires-Python: >=3.8,<4.0
Classifier: License :: OSI Approved :: MIT License
Classifier: Programming Language :: Python :: 3
Classifier: Programming Language :: Python :: 3.8
Classifier: Programming Language :: Python :: 3.9
Requires-Dist: numpy (>=1.19.2,<2.0.0)
Requires-Dist: opencv-python (>=4.4.0,<5.0.0)
Requires-Dist: remotevbox (>=1.0.0,<2.0.0)
Project-URL: Repository, https://github.com/jacopofar/virtualbox-helper
